postgraas_server/__init__.py
postgraas_server/configuration.py
postgraas_server/create_app.py
postgraas_server/init_db.py
postgraas_server/management_database.py
postgraas_server/management_resources.py
postgraas_server/postgraas_api.py
postgraas_server/prometheus_app.py
postgraas_server/utils.py
postgraas_server/backends/__init__.py
postgraas_server/backends/exceptions.py
postgraas_server/backends/docker/__init__.py
postgraas_server/backends/docker/create_db.py
postgraas_server/backends/docker/postgres_instance_driver.py
postgraas_server/backends/postgres_cluster/__init__.py
postgraas_server/backends/postgres_cluster/postgres_cluster_driver.py
postgraas_server-2.1.4.dist-info/AUTHORS.rst
postgraas_server-2.1.4.dist-info/LICENSE.txt
postgraas_server-2.1.4.dist-info/METADATA
postgraas_server-2.1.4.dist-info/WHEEL
postgraas_server-2.1.4.dist-info/entry_points.txt
postgraas_server-2.1.4.dist-info/top_level.txt
postgraas_server-2.1.4.dist-info/RECORD
