Metadata-Version: 2.1
Name: postgraas-server
Version: 2.1.4
Summary: Postgraas is a super simple PostgreSQL-as-a-service
Home-page: http://postgraas-server.readthedocs.io
Author: Sebastian Neubauer
Author-email: sebineubauer@gmail.com
License: Apache-2
Platform: UNKNOWN
Classifier: Development Status :: 4 - Beta
Classifier: Programming Language :: Python :: 2.7
Classifier: Programming Language :: Python :: 3.5
Classifier: Programming Language :: Python :: 3.6
Requires-Dist: blinker
Requires-Dist: flask
Requires-Dist: flask-restful
Requires-Dist: flask-sqlalchemy
Requires-Dist: psycopg2
Requires-Dist: raven[flask]
Provides-Extra: docker
Requires-Dist: docker ; extra == 'docker'
Provides-Extra: prometheus
Requires-Dist: prometheus-client ; extra == 'prometheus'
Provides-Extra: secure_config
Requires-Dist: secure-config ; extra == 'secure_config'
